pymediasoup/__init__.py
pymediasoup/__version__.py
pymediasoup/consumer.py
pymediasoup/data_consumer.py
pymediasoup/data_producer.py
pymediasoup/device.py
pymediasoup/emitter.py
pymediasoup/errors.py
pymediasoup/handlers/__init__.py
pymediasoup/handlers/aiortc_handler.py
pymediasoup/handlers/handler_interface.py
pymediasoup/handlers/sdp/__init__.py
pymediasoup/handlers/sdp/common_utils.py
pymediasoup/handlers/sdp/media_section.py
pymediasoup/handlers/sdp/remote_sdp.py
pymediasoup/handlers/sdp/unified_plan_utils.py
pymediasoup/models/__init__.py
pymediasoup/models/handler_interface.py
pymediasoup/models/transport.py
pymediasoup/ortc.py
pymediasoup/producer.py
pymediasoup/rtp_parameters.py
pymediasoup/scalability_modes.py
pymediasoup/sctp_parameters.py
pymediasoup/transport.py
pymediasoup/types/webrtc.py
huddle01_pymediasoup-1.2.1.dist-info/LICENSE
huddle01_pymediasoup-1.2.1.dist-info/METADATA
huddle01_pymediasoup-1.2.1.dist-info/WHEEL
huddle01_pymediasoup-1.2.1.dist-info/RECORD
