Metadata-Version: 2.3
Name: huddle01-pymediasoup
Version: 1.2.1
Summary: Derived version of original pymediasoup, for Huddle01
License: MIT
Author: Akash Mondal
Author-email: akmo3901@gmail.com
Requires-Python: >=3.9,<4.0
Classifier: License :: OSI Approved :: MIT License
Classifier: Programming Language :: Python :: 3
Classifier: Programming Language :: Python :: 3.9
Classifier: Programming Language :: Python :: 3.10
Classifier: Programming Language :: Python :: 3.11
Classifier: Programming Language :: Python :: 3.12
Classifier: Programming Language :: Python :: 3.13
Requires-Dist: aiortc (>=1.10.1,<2.0.0)
Requires-Dist: h264-profile-level-id (>=1.0.0,<2.0.0)
Requires-Dist: pydantic (>=1.10.17,<3.0.0)
Requires-Dist: pyee (>=11.1.0,<12.0.0)
Requires-Dist: sdp-transform (>=1.1.0,<2.0.0)
Project-URL: Repository, https://github.com/Huddle01/pymediasoup
